{
  "SSR武器": [
    "八岐断雷枪",
    "鬼泪村正",
    "岚·不鸣之刃",
    "神使·沧溟",
    "怒鲤双生",
    "赤焰龙息",
    "风宿·苍龙",
    "织炎",
    "炎宿·朱雀",
    "爱疯XXX",
    "苍雪祝神铃",
    "亡魂之音",
    "如龙临渊",
    "风信鹤羽",
    "百雷·拂晓",
    "雷鸣剑",
    "风妖镰鼬",
    "断潮",
    "雷狱光剑",
    "御火芭蕉扇",
    "冰岚折扇",
    "龙毫笔",
    "雷宿·麒麟",
    "天音灵箫",
    "漩雷一文字",
    "苍月战刃",
    "伏溟九渊",
    "天晶苦无",
    "广罗天寒",
    "紫电白虹",
    "祝融",
    "龙神飨宴",
    "真·凌玉弓",
    "神炎杖",
    "风月含袖",
    "三日月雷切",
    "尽滅",
    "巨阙·缚日",
    "仙羽聆雪",
    "虎啸",
    "雷契·化龙",
    "绯霆",
    "丛云之霜羽",
    "绮梦",
    "百练",
    "破云"
  ],
  "忍者": [
    "小黑·龙焰",
    "小黑·炎魂",
    "阿力·雷兽",
    "阿力·超威",
    "琳·雪舞",
    "琳·神乐",
    "苍牙·鬼狩",
    "苍牙·绯斩",
    "小椒·星闪",
    "小椒·神炎",
    "伊鹤·瞬翎",
    "洛青·龙吟",
    "银枭·奔雷",
    "老板娘·猫太",
    "卫鲤·剑心",
    "兮兰·冰羽",
    "紫原·鬼斩",
    "隼白·夜叉",
    "舞·不知火",
    "戌时·风铭",
    "伊鹤·霜刃",
    "兮兰·寒绡",
    "小椒·双焰"
  ],
  "忍阶": [
    "不入流",
    "    忍生",
    "    下忍",
    "    中忍",
    "    上忍",
    "    狂忍",
    "    超忍",
    "    影忍",
    "    极忍",
    "    幻忍",
    "    绝忍",
    "    禁忍",
    "    鹰扬",
    "    魁首",
    "    鬼滅",
    "    铭印师",
    "    诡兵尽藏",
    "    表情帝",
    "    神行者",
    "    神弈",
    "    破煞",
    "    百变者",
    "    王牌战队",
    "    猎魂",
    "    猎魁",
    "    猎王",
    "    牌仙",
    "    收藏家",
    "    幻术使",
    "    幻变无常",
    "    天命",
    "    天元百强",
    "    天元十忍",
    "    天元一番",
    "    名师",
    "    千面人",
    "    匠人",
    "    冠绝",
    "    冠军战队",
    "    云集",
    "    主宰",
    "    万化千面",
    "荧·双焰"
  ],
  "时装": [
    "黄巾·小黑",
    "铁甲·小黑",
    "土豆·小黑",
    "炎魂·小黑",
    "炫彩·小黑",
    "电音·小黑",
    "冲浪·小黑",
    "宇宙·小黑",
    "贺春·小黑",
    "粉红·小黑",
    "铜甲·小黑",
    "无面·小黑",
    "街球·小黑",
    "百炼·小黑",
    "J0KER·小黑",
    "Pop Star",
    "Rock Star",
    "王牌魔术",
    "鎏金·龙焰",
    "龙焰·觉醒",
    "村夫·阿力",
    "功夫·阿力",
    "雷兽·阿力",
    "牛仔·阿力",
    "宗师·阿力",
    "煞面·阿力",
    "圣诞·阿力",
    "贺春·阿力",
    "潜水·阿力",
    "侠客·阿力",
    "鬼首·阿力",
    "玄甲·阿力",
    "墨客·阿力",
    "趋全垒打",
    "聚核裂变",
    "弥生·琳",
    "桃姬·琳",
    "神乐·琳",
    "巫女·琳",
    "女仆·琳",
    "兔女郎·琳",
    "青行姬·琳",
    "樱花·琳",
    "芳青·琳",
    "夏梦·琳",
    "蓝雪·琳",
    "镜花·琳",
    "嫣华·琳",
    "墨龙赤鲤",
    "花颜中",
    "虚拟歌姬",
    "霜叶红·琳",
    "稚黑·琳",
    "青尾之海",
    "雪舞·觉醒",
    "紫朵·雪舞",
    "苍牙",
    "魂·苍牙",
    "深海·苍牙",
    "苍雪飞狐",
    "猫灵·苍牙",
    "收割者",
    "追风少年",
    "黑暗渡使",
    "乘风破浪",
    "共潮生",
    "风林火山",
    "潇碧惊风",
    "柠檬小椒",
    "神炎·小椒",
    "桃花·小椒",
    "放课·小椒",
    "冲鸭·小椒",
    "蹦跳·小椒",
    "闹春·小椒",
    "樱舞·小椒",
    "航海·小椒",
    "雪中红裘",
    "金蕊傲春",
    "锦鲤抄",
    "雪霁莲欢",
    "喵鸣·小椒",
    "软糖甜星",
    "科学怪熊",
    "怦然星动",
    "浆果与兔",
    "黄衫·伊鹤",
    "瞬翎·伊鹤",
    "夜色春华",
    "翡歌咏叹",
    "夜梦星灵",
    "松烟锦年",
    "宴红堂",
    "幽兰蝶梦",
    "子衿·洛青",
    "龙吟·洛青",
    "海祭·洛青",
    "长麓逐枫",
    "腾狮戏浪",
    "深红魅影",
    "青鳞渡川",
    "学衿·洛青",
    "奔雷·银枭",
    "青离·银枭",
    "虹羽逐浪",
    "银翼骇客",
    "芝兰·老板娘",
    "猫太·老板娘",
    "碧海风轻",
    "红罗吹雪",
    "和日之煦",
    "极道·卫鲤",
    "紫罗·卫鲤",
    "鲤跃居",
    "趴趴雪熊",
    "弈者·卫鲤",
    "波光丽影",
    "清悦·兮兰",
    "芸舞·兮兰",
    "芭蕾之最",
    "鬼斩·紫原",
    "天青·紫原",
    "棋士·紫原",
    "摇滚狂想",
    "白棘裁决者",
    "莲波竞红",
    "紫降·隼白",
    "暗鸦断罪者",
    "庆升平",
    "报恩桃·戌时",
    "胜利之星",
    "不知火·舞",
    "炎龙铠甲",
    "琳儿小叮当",
    "剑心·卫鲤",
    "冰语·兮兰",
    "夜叉·隼白"
  ],
  "皮肤": [
    "风铭·戌时",
    "吞耀",
    "流冷",
    "时刃"
  ]
}